CHANGES.txt
LICENSE.txt
MANIFEST.in
setup.py
M5.egg-info/PKG-INFO
M5.egg-info/SOURCES.txt
M5.egg-info/dependency_links.txt
M5.egg-info/requires.txt
M5.egg-info/top_level.txt
docs/tutorial/_footer.html
docs/tutorial/_head.html
docs/tutorial/app_packaging.md
docs/tutorial/background.md
docs/tutorial/docs.css
docs/tutorial/index.md
docs/tutorial/m5_command.md
docs/tutorial/philosophy.md
docs/tutorial/sim_console.md
jquery-mobile/.DS_Store
jquery-mobile/jquery.mobile-1.0b1.css
jquery-mobile/jquery.mobile-1.0b1.js
jquery-mobile/jquery.mobile-1.0b1.min.css
jquery-mobile/jquery.mobile-1.0b1.min.js
jquery-mobile/jquery.mobile-1.0b2.css
jquery-mobile/jquery.mobile-1.0b2.js
jquery-mobile/jquery.mobile-1.0b2.min.css
jquery-mobile/jquery.mobile-1.0b2.min.js
jquery-mobile/images/ajax-loader.png
jquery-mobile/images/icon-search-black.png
jquery-mobile/images/icons-18-black.png
jquery-mobile/images/icons-18-white.png
jquery-mobile/images/icons-36-black.png
jquery-mobile/images/icons-36-white.png
lib/.DS_Store
lib/iscroll-lite.js
lib/iscroll.js
lib/jquery-1.6.1.min.js
lib/jquery.tmpl.min.js
lib/m5.boot.js
lib/m5.cloud.js
lib/m5.env.js
lib/m5.remote_console.js
lib/m5.simplestorage.js
lib/m5.simulator.css
lib/m5.simulator.js
lib/m5.support.js
lib/scrollability.css
lib/scrollability.js
lib/simpanel.html
lib/twitter.scrollview.js
lib/zepto.js
lib/zepto.min.js
lib/assets/devices.json
lib/assets/disk-black.png
lib/assets/droid.png
lib/assets/iphone.png
lib/assets/iphone4.psd
lib/assets/minus-circle.png
lib/scottp-scrollability/scrollability.js
m5/__init__.py
m5/app.py
m5/compiler.py
m5/m5
m5/server.py
templates/application.js
templates/m5.env.development.js
templates/m5.env.production.js
templates/manifest.json
templates/cities/app.m5.html
templates/cities/appjqt.m5.html
templates/cities/application.js
templates/cities/data/city_details.json
templates/oscars/app.m5.html
templates/oscars/application.js
templates/oscars/m5.env.development.js
templates/oscars/m5.env.production.js
templates/oscars/manifest.json
templates/oscars/data/city_details.json
templates/stub/app.m5.html