Metadata-Version: 1.0
Name: M5
Version: 0.3.2
Summary: HTML5 mobile app toolkit
Home-page: http://m5apps.org/
Author: Scott Persinger
Author-email: scottpersinger@gmail.com
License: LICENSE.txt
Keywords: html5 mobile apps
Platform: UNKNOWN
